smdata/__init__.py
smdata/misc.py
smdata/serealizers.py
smdata-1.6.4.dist-info/WHEEL
smdata-1.6.4.dist-info/entry_points.txt
smdata-1.6.4.dist-info/METADATA
smdata-1.6.4.dist-info/RECORD
