Metadata-Version: 2.3
Name: smdata
Version: 1.6.4
Summary: Small package with named shared memory data structures
Author: Xenely
Requires-Dist: orjson>=3.11.4
Requires-Python: >=3.10
